setup.cfg
setup.py
src/gentoo/__init__.py
src/gentoo/main.py
src/tenyks_contrib.egg-info/PKG-INFO
src/tenyks_contrib.egg-info/SOURCES.txt
src/tenyks_contrib.egg-info/dependency_links.txt
src/tenyks_contrib.egg-info/entry_points.txt
src/tenyks_contrib.egg-info/requires.txt
src/tenyks_contrib.egg-info/top_level.txt
src/tenyks_contrib.egg-info/zip-safe
src/tenyksafk/__init__.py
src/tenyksafk/main.py
src/tenyksbrain/__init__.py
src/tenyksbrain/core.py
src/tenyksddate/__init__.py
src/tenyksddate/main.py
src/tenyksfeeds/__init__.py
src/tenyksfeeds/main.py
src/tenyksfun/__init__.py
src/tenyksfun/main.py
src/tenykshahameter/__init__.py
src/tenykshahameter/main.py
src/tenykshi/__init__.py
src/tenykshi/main.py
src/tenyksleetpoints/__init__.py
src/tenyksleetpoints/main.py
src/tenykslinkscraper/__init__.py
src/tenykslinkscraper/main.py
src/tenykslogger/__init__.py
src/tenykslogger/main.py
src/tenyksmusic/__init__.py
src/tenyksmusic/main.py
src/tenyksoutofcontext/__init__.py
src/tenyksoutofcontext/main.py
src/tenykspoll/__init__.py
src/tenykspoll/main.py
src/tenyksscripts/__init__.py
src/tenyksscripts/main.py
src/tenyksscripts/scripts/8ball.py
src/tenyksscripts/scripts/__init__.py
src/tenyksscripts/scripts/aww.py
src/tenyksscripts/scripts/catfact.py
src/tenyksscripts/scripts/catnip.py
src/tenyksscripts/scripts/dark.py
src/tenyksscripts/scripts/ddgdefine.py
src/tenyksscripts/scripts/forking.py
src/tenyksscripts/scripts/githubstatus.py
src/tenyksscripts/scripts/goatthrower.py
src/tenyksscripts/scripts/goattower.py
src/tenyksscripts/scripts/hextime.py
src/tenyksscripts/scripts/jnerulastimezone.py
src/tenyksscripts/scripts/michiganfact.py
src/tenyksscripts/scripts/numbersapi.py
src/tenyksscripts/scripts/orihaus_games.py
src/tenyksscripts/scripts/ping.py
src/tenyksscripts/scripts/ponder.py
src/tenyksscripts/scripts/portlandfact.py
src/tenyksscripts/scripts/printerfact.py
src/tenyksscripts/scripts/stallman.py
src/tenyksscripts/scripts/stocks.py
src/tenyksscripts/scripts/urbandictionary.py
src/tenyksscripts/scripts/user_stats.py
src/tenyksscripts/scripts/usstatus.py
src/tenyksscripts/scripts/tests/__init__.py
src/tenyksscripts/scripts/tests/hextime_tests.py
src/tenyksscripts/scripts/tests/ping_tests.py
src/tenyksscripts/scripts/tests/ponder_tests.py
