Metadata-Version: 1.0
Name: tenyks-contrib
Version: 0.2.1
Summary: Contributed services for the tenyks IRC bot
Home-page: https://github.com/kyleterry/tenyks-contrib
Author: Kyle Terry
Author-email: kyle@kyleterry.com
License: LICENSE
Keywords: clients tenyks ircbot services tenyks-service
Platform: UNKNOWN
